fpga_hardware/cores/md5/pancham_round.v
/*****************************************************************
 Pancham is an MD5 compliant IP core for cryptographic applicati
 -ons. 
 Copyright (C) 2003  Swapnajit Mittra, Project VeriPage
 (Contact email: verilog_tutorial at hotmail.com
  Website      : http://www.angelfire.com/ca/verilog)

 This library is free software; you can redistribute it and/or
 modify it under the terms of the GNU Lesser General Public
 License as published by the Free Software Foundation; either
 version 2.1 of the License, or (at your option) any later version.
 
 This library is distributed in the hope that it will be useful,
 but WITHOUT ANY WARRANTY; without even the implied warranty of
 MERCHANTABILITY or FITNESS FOR A PARTICULAR PURPOSE.  See the GNU
 Lesser General Public License for more details.
 
 You should have received a copy of the GNU Lesser General Public
 License along with this library; if not, write to the 
 
 Free Software Foundation, Inc.
 59 Temple Place, Suite 330
 Boston, MA  02111-1307 
 USA
 ******************************************************************/
/* 
 * pancham_round performs the rounds 1-4 of the MD5 algorithm 
 * described in RFC1321 for a 128-bit long input message. 
 * 
 * Inputs: [abcd m[k] s abs(sin(2*pi*t/64))] as described 
 *         in RFC1321.Also the round number (1-4).
 * 
 * Outputs: the modified 'a' value as describes in RFC1321
 *         on the left hand side of the round #n equation.
 * 
 */

`define ROUND1 2'b00
`define ROUND2 2'b01
`define ROUND3 2'b10
`define ROUND4 2'b11

module pancham_round (
     a
   , b
   , c
   , d
   , m
   , s
   , t 
   , round

   , next_a
   );

input  [31:0] a;
input  [31:0] b;
input  [31:0] c;
input  [31:0] d;
input  [31:0] m;          // Note that for a 128-bit long input message, X[k] = M[k] = m
input  [31:0] s;
input  [31:0] t;          // t-th sample of abs(sin(i)), i = 1, 2, ..., 64
input   [1:0] round;      // round number (1-4).

output [31:0] next_a;

wire  [31:0] a;         // 
wire  [31:0] b;
wire  [31:0] c;
wire  [31:0] d;
wire  [31:0] m;
wire  [31:0] s;
wire  [31:0] t;
wire   [1:0] round;

reg   [31:0] next_a;

reg   [31:0] add_result;
reg   [31:0] rotate_result1;
reg   [31:0] rotate_result2;

always @(a
   or    b
   or    c
   or    d
   or    m
   or    s
   or    t
   or    round) begin // {
   case (round)
   `ROUND1: 
   begin // {
      add_result = (a + F(b,c,d) + m + t);
      rotate_result1 = add_result << s;
      rotate_result2 = add_result >> (32-s);
      next_a = b + (rotate_result1 | rotate_result2);
   end // }
   `ROUND2: 
   begin // {
      add_result = (a + G(b,c,d) + m + t);
      rotate_result1 = add_result << s;
      rotate_result2 = add_result >> (32-s);
      next_a = b + (rotate_result1 | rotate_result2);
   end // }
   `ROUND3:
   begin // {
      add_result = (a + H(b,c,d) + m + t);
      rotate_result1 = add_result << s;
      rotate_result2 = add_result >> (32-s);
      next_a = b + (rotate_result1 | rotate_result2);
   end // }
   `ROUND4:
   begin // {
      add_result = (a + I(b,c,d) + m + t);
      rotate_result1 = add_result << s;
      rotate_result2 = add_result >> (32-s);
      next_a = b + (rotate_result1 | rotate_result2);
   end // }
   endcase
end // }

//--------------------------------
//
// Function declarations
//
//--------------------------------
// Step 4 functions F, G, H and I
function [31:0] F;
input [31:0] x, y, z;
begin // {
   F = (x&y)|((~x)&z);
end // }
endfunction // }

function [31:0] G;
input [31:0] x, y, z;
begin // {
   G = (x&z)|(y&(~z));
end // }
endfunction 

function [31:0] H;
input [31:0] x, y, z;
begin // {
   H = (x^y^z);
end // }
endfunction 

function [31:0] I;
input [31:0] x, y, z;
begin // {
   I = (y^(x|(~z)));
end // }
endfunction 

endmodule

fpga_hardware/cores/md5/pancham.v
/*****************************************************************
 Pancham is an MD5 compliant IP core for cryptographic 
 applications. 
 Copyright (C) 2003  Swapnajit Mittra, Project VeriPage
 (Contact email: verilog_tutorial at hotmail.com
  Website      : http://www.angelfire.com/ca/verilog)

 This library is free software; you can redistribute it and/or
 modify it under the terms of the GNU Lesser General Public
 License as published by the Free Software Foundation; either
 version 2.1 of the License, or (at your option) any later version.
 
 This library is distributed in the hope that it will be useful,
 but WITHOUT ANY WARRANTY; without even the implied warranty of
 MERCHANTABILITY or FITNESS FOR A PARTICULAR PURPOSE.  See the GNU
 Lesser General Public License for more details.
 
 You should have received a copy of the GNU Lesser General Public
 License along with this library; if not, write to the 
 
 Free Software Foundation, Inc.
 59 Temple Place, Suite 330
 Boston, MA  02111-1307 
 USA
 ******************************************************************/
/* 
 * This is the main module that computes a 128-bit message 
 * digest from a maximum of 512-bit long input message using
 * MD5 algorithm.
 *
 * Modified by Matthew Hicks (mdhicks@gmail.com)
 *   Input from 128-bit to 512-bit
 *   Hold valid outputs
 *   Carry over constants between encryptions
 *   Support for arbitrary size encryption
 *   Address some Verilator warnings
 *
 */

`include "pancham.h"

/* verilator lint_off LITENDIAN */
/* verilator lint_off UNOPTFLAT */

module pancham (
        clk
      , rst	
      , msg_padded
      , msg_in_valid

      , msg_output
      , msg_out_valid
      , ready
      );

//--------------------------------
//
// Input/Output declarations 
//
//--------------------------------
input          clk;                      // input clock
input          rst;                    // global rst
input  [0:511] msg_padded;               // input message, already padded
input          msg_in_valid;             // input message is valid, active high
                                       
output [0:127] msg_output;               // output message, always 128 bit wide
output         msg_out_valid;            // if asserted, output message is valid
output         ready;                    // the core is ready for an input message

//--------------------------------
//
// Variable declarations
//
//--------------------------------
// inputs
wire          clk;        
wire          rst;
wire  [0:511] msg_padded;          
wire          msg_in_valid;

// output                 
wire  [0:127] msg_output; 
reg           msg_out_valid;
wire          ready;

// scratch pads
reg    [0:1] round;
reg   [0:31] a;
reg   [0:31] A;
reg   [0:31] AA;
reg   [0:31] next_A;
reg   [0:31] b;
reg   [0:31] B;
reg   [0:31] BB;
reg   [0:31] next_B;
reg   [0:31] c;
reg   [0:31] C;
reg   [0:31] CC;
reg   [0:31] next_C;
reg   [0:31] d;
reg   [0:31] D;
reg   [0:31] DD;
reg   [0:31] next_D;
reg   [0:31] m;
reg   [0:31] s; 
reg   [0:31] t;
reg    [3:0] phase;         // Counter to determine 16 phases within each round.
wire  [0:31] next_a;
reg    [7:0] current_state; 
reg    [7:0] next_state;
reg [8*11:1] ascii_state;

//--------------------------------
//
// Parameter definitions
// 
//--------------------------------

parameter SALT_A         = 32'h67452301;
parameter SALT_B         = 32'hefcdab89;
parameter SALT_C         = 32'h98badcfe;
parameter SALT_D         = 32'h10325476;

parameter ONE            = 72'h1;
                         
parameter IDLE_BIT       = 0;
parameter IDLE           = ONE << IDLE_BIT;
                         
parameter ROUND1_BIT     = 1;
parameter ROUND1         = ONE << ROUND1_BIT;
                         
parameter ROUND2_BIT     = 2;
parameter ROUND2         = ONE << ROUND2_BIT;
                         
parameter ROUND3_BIT     = 3;
parameter ROUND3         = ONE << ROUND3_BIT;
                         
parameter ROUND4_BIT     = 4;
parameter ROUND4         = ONE << ROUND4_BIT;
                         
parameter FINISH_OFF_BIT = 5;
parameter FINISH_OFF     = ONE << FINISH_OFF_BIT;

parameter TURN_ARND_BIT  = 6;
parameter TURN_ARND      = ONE << TURN_ARND_BIT;


//--------------------------------
//
// Submodule instantiation
//
//--------------------------------
pancham_round ROUND (
     .a      (a    ) 
   , .b      (b    ) 
   , .c      (c    ) 
   , .d      (d    ) 
   , .m      (m    )
   , .s      (s    ) 
   , .t      (t    ) 
   , .round  (round)

   , .next_a (next_a) 
);

//--------------------------------
//
// Actual code starts here
//
//--------------------------------

always @(current_state
   or    msg_in_valid
   or    A
   or    B
   or    C
   or    D
   or    phase
   or    msg_padded
   or    next_a
   or    AA
   or    BB
   or    CC
   or    DD

   ) begin // {
   round = `ROUND1;
   next_A = A;
   next_B = B; 
   next_C = C; 
   next_D = D;
   
   a = 32'h0;
   b = 32'h0;
   c = 32'h0;
   d = 32'h0;
   m = 32'h0;
   s = 32'h0;
   t = 32'h0;
   
   next_state = current_state; 

   case (1'b1) // synopsys full_case parallel_case 

   current_state[IDLE_BIT]: 
   begin // {
      // synopsys translate_off
      ascii_state = "IDLE";
      // synopsys translate_on

      if (msg_in_valid)  
         next_state = ROUND1[7:0];
   end // }

   //----------------------------------------------------------------
   //--------------------------- ROUND 1 ----------------------------
   //----------------------------------------------------------------
   current_state[ROUND1_BIT]: 
   begin // {
      // synopsys translate_off
      ascii_state = "ROUND1";
      // synopsys translate_on

      round = `ROUND1;

      case (phase)
      4'b0000: begin a=A; b=B; c=C; d=D; m=msg_padded[480:511]; s=32'd07; t= `T_1; next_A=next_a; end
      4'b0001: begin a=D; b=A; c=B; d=C; m=msg_padded[448:479]; s=32'd12; t= `T_2; next_D=next_a; end
      4'b0010: begin a=C; b=D; c=A; d=B; m=msg_padded[416:447]; s=32'd17; t= `T_3; next_C=next_a; end
      4'b0011: begin a=B; b=C; c=D; d=A; m=msg_padded[384:415]; s=32'd22; t= `T_4; next_B=next_a; end
      4'b0100: begin a=A; b=B; c=C; d=D; m=msg_padded[352:383]; s=32'd07; t= `T_5; next_A=next_a; end
      4'b0101: begin a=D; b=A; c=B; d=C; m=msg_padded[320:351]; s=32'd12; t= `T_6; next_D=next_a; end
      4'b0110: begin a=C; b=D; c=A; d=B; m=msg_padded[288:319]; s=32'd17; t= `T_7; next_C=next_a; end
      4'b0111: begin a=B; b=C; c=D; d=A; m=msg_padded[256:287]; s=32'd22; t= `T_8; next_B=next_a; end
      4'b1000: begin a=A; b=B; c=C; d=D; m=msg_padded[224:255]; s=32'd07; t= `T_9; next_A=next_a; end
      4'b1001: begin a=D; b=A; c=B; d=C; m=msg_padded[192:223]; s=32'd12; t=`T_10; next_D=next_a; end
      4'b1010: begin a=C; b=D; c=A; d=B; m=msg_padded[160:191]; s=32'd17; t=`T_11; next_C=next_a; end
      4'b1011: begin a=B; b=C; c=D; d=A; m=msg_padded[128:159]; s=32'd22; t=`T_12; next_B=next_a; end
      4'b1100: begin a=A; b=B; c=C; d=D; m=msg_padded[96:127];  s=32'd7;  t=`T_13; next_A=next_a; end
      4'b1101: begin a=D; b=A; c=B; d=C; m=msg_padded[64:95];   s=32'd12; t=`T_14; next_D=next_a; end
      4'b1110: begin a=C; b=D; c=A; d=B; m=msg_padded[32:63];   s=32'd17; t=`T_15; next_C=next_a; end
      4'b1111: begin a=B; b=C; c=D; d=A; m=msg_padded[0:31];    s=32'd22; t=`T_16; next_B=next_a; end
      endcase

      if (phase == 4'b1111)
         next_state = ROUND2[7:0];
   end // }
   //----------------------------------------------------------------
   //--------------------------- ROUND 2 ----------------------------
   //----------------------------------------------------------------

   current_state[ROUND2_BIT]:
   begin // {
      // synopsys translate_off
      ascii_state = "ROUND2";
      // synopsys translate_on
 
      round = `ROUND2;
      case (phase) 
      4'b0000: begin a=A; b=B; c=C; d=D; m=msg_padded[448:479]; s=32'd05; t=`T_17; next_A=next_a; end
      4'b0001: begin a=D; b=A; c=B; d=C; m=msg_padded[288:319]; s=32'd09; t=`T_18; next_D=next_a; end
      4'b0010: begin a=C; b=D; c=A; d=B; m=msg_padded[128:159]; s=32'd14; t=`T_19; next_C=next_a; end
      4'b0011: begin a=B; b=C; c=D; d=A; m=msg_padded[480:511]; s=32'd20; t=`T_20; next_B=next_a; end
      4'b0100: begin a=A; b=B; c=C; d=D; m=msg_padded[320:351]; s=32'd05; t=`T_21; next_A=next_a; end
      4'b0101: begin a=D; b=A; c=B; d=C; m=msg_padded[160:191]; s=32'd09; t=`T_22; next_D=next_a; end
      4'b0110: begin a=C; b=D; c=A; d=B; m=msg_padded[0:31];    s=32'd14; t=`T_23; next_C=next_a; end
      4'b0111: begin a=B; b=C; c=D; d=A; m=msg_padded[352:383]; s=32'd20; t=`T_24; next_B=next_a; end
      4'b1000: begin a=A; b=B; c=C; d=D; m=msg_padded[192:223]; s=32'd05; t=`T_25; next_A=next_a; end
      4'b1001: begin a=D; b=A; c=B; d=C; m=msg_padded[32:63];   s=32'd9;  t=`T_26; next_D=next_a; end
      4'b1010: begin a=C; b=D; c=A; d=B; m=msg_padded[384:415]; s=32'd14; t=`T_27; next_C=next_a; end
      4'b1011: begin a=B; b=C; c=D; d=A; m=msg_padded[224:255]; s=32'd20; t=`T_28; next_B=next_a; end
      4'b1100: begin a=A; b=B; c=C; d=D; m=msg_padded[64:95];   s=32'd05; t=`T_29; next_A=next_a; end
      4'b1101: begin a=D; b=A; c=B; d=C; m=msg_padded[416:447]; s=32'd09; t=`T_30; next_D=next_a; end
      4'b1110: begin a=C; b=D; c=A; d=B; m=msg_padded[256:287]; s=32'd14; t=`T_31; next_C=next_a; end
      4'b1111: begin a=B; b=C; c=D; d=A; m=msg_padded[96:127];  s=32'd20; t=`T_32; next_B=next_a; end
      endcase

      if (phase == 4'b1111)
         next_state = ROUND3[7:0];
   end // }
   //----------------------------------------------------------------
   //--------------------------- ROUND 3 ----------------------------
   //----------------------------------------------------------------
 
   current_state[ROUND3_BIT]:
   begin // {
      // synopsys translate_off
      ascii_state = "ROUND3";
      // synopsys translate_on
 
      round = `ROUND3;
      case (phase) 
      4'b0000: begin a=A; b=B; c=C; d=D; m=msg_padded[320:351]; s=32'd04; t=`T_33; next_A=next_a; end
      4'b0001: begin a=D; b=A; c=B; d=C; m=msg_padded[224:255]; s=32'd11; t=`T_34; next_D=next_a; end
      4'b0010: begin a=C; b=D; c=A; d=B; m=msg_padded[128:159]; s=32'd16; t=`T_35; next_C=next_a; end
      4'b0011: begin a=B; b=C; c=D; d=A; m=msg_padded[32:63];   s=32'd23; t=`T_36; next_B=next_a; end
      4'b0100: begin a=A; b=B; c=C; d=D; m=msg_padded[448:479]; s=32'd04; t=`T_37; next_A=next_a; end
      4'b0101: begin a=D; b=A; c=B; d=C; m=msg_padded[352:383]; s=32'd11; t=`T_38; next_D=next_a; end
      4'b0110: begin a=C; b=D; c=A; d=B; m=msg_padded[256:287]; s=32'd16; t=`T_39; next_C=next_a; end
      4'b0111: begin a=B; b=C; c=D; d=A; m=msg_padded[160:191]; s=32'd23; t=`T_40; next_B=next_a; end
      4'b1000: begin a=A; b=B; c=C; d=D; m=msg_padded[64:95];   s=32'd04; t=`T_41; next_A=next_a; end
      4'b1001: begin a=D; b=A; c=B; d=C; m=msg_padded[480:511]; s=32'd11; t=`T_42; next_D=next_a; end
      4'b1010: begin a=C; b=D; c=A; d=B; m=msg_padded[384:415]; s=32'd16; t=`T_43; next_C=next_a; end
      4'b1011: begin a=B; b=C; c=D; d=A; m=msg_padded[288:319]; s=32'd23; t=`T_44; next_B=next_a; end
      4'b1100: begin a=A; b=B; c=C; d=D; m=msg_padded[192:223]; s=32'd04; t=`T_45; next_A=next_a; end
      4'b1101: begin a=D; b=A; c=B; d=C; m=msg_padded[96:127];  s=32'd11; t=`T_46; next_D=next_a; end
      4'b1110: begin a=C; b=D; c=A; d=B; m=msg_padded[0:31];    s=32'd16; t=`T_47; next_C=next_a; end
      4'b1111: begin a=B; b=C; c=D; d=A; m=msg_padded[416:447]; s=32'd23; t=`T_48; next_B=next_a; end
      endcase

      if (phase == 4'b1111)
         next_state = ROUND4[7:0];
   end // }
   //----------------------------------------------------------------
   //--------------------------- ROUND 4 ----------------------------
   //----------------------------------------------------------------
 
   current_state[ROUND4_BIT]:
   begin // {
      // synopsys translate_off
      ascii_state = "ROUND4";
      // synopsys translate_on
 
      round = `ROUND4;
      case (phase)
      4'b0000: begin a=A; b=B; c=C; d=D; m=msg_padded[480:511]; s=32'd06; t=`T_49; next_A=next_a; end
      4'b0001: begin a=D; b=A; c=B; d=C; m=msg_padded[256:287]; s=32'd10; t=`T_50; next_D=next_a; end
      4'b0010: begin a=C; b=D; c=A; d=B; m=msg_padded[32:63];   s=32'd15; t=`T_51; next_C=next_a; end
      4'b0011: begin a=B; b=C; c=D; d=A; m=msg_padded[320:351]; s=32'd21; t=`T_52; next_B=next_a; end
      4'b0100: begin a=A; b=B; c=C; d=D; m=msg_padded[96:127];  s=32'd06; t=`T_53; next_A=next_a; end
      4'b0101: begin a=D; b=A; c=B; d=C; m=msg_padded[384:415]; s=32'd10; t=`T_54; next_D=next_a; end
      4'b0110: begin a=C; b=D; c=A; d=B; m=msg_padded[160:191]; s=32'd15; t=`T_55; next_C=next_a; end
      4'b0111: begin a=B; b=C; c=D; d=A; m=msg_padded[448:479]; s=32'd21; t=`T_56; next_B=next_a; end
      4'b1000: begin a=A; b=B; c=C; d=D; m=msg_padded[224:255]; s=32'd06; t=`T_57; next_A=next_a; end
      4'b1001: begin a=D; b=A; c=B; d=C; m=msg_padded[0:31];    s=32'd10; t=`T_58; next_D=next_a; end
      4'b1010: begin a=C; b=D; c=A; d=B; m=msg_padded[288:319]; s=32'd15; t=`T_59; next_C=next_a; end
      4'b1011: begin a=B; b=C; c=D; d=A; m=msg_padded[64:95];   s=32'd21; t=`T_60; next_B=next_a; end
      4'b1100: begin a=A; b=B; c=C; d=D; m=msg_padded[352:383]; s=32'd06; t=`T_61; next_A=next_a; end
      4'b1101: begin a=D; b=A; c=B; d=C; m=msg_padded[128:159]; s=32'd10; t=`T_62; next_D=next_a; end
      4'b1110: begin a=C; b=D; c=A; d=B; m=msg_padded[416:447]; s=32'd15; t=`T_63; next_C=next_a; end
      4'b1111: begin a=B; b=C; c=D; d=A; m=msg_padded[192:223]; s=32'd21; t=`T_64; next_B=next_a; end
      endcase

      if (phase == 4'b1111)
         next_state = FINISH_OFF[7:0];
   end // }
   //----------------------------------------------------------------

   current_state[FINISH_OFF_BIT]: 
   begin // {
      // synopsys translate_off
      ascii_state = "FINISH_OFF";
      // synopsys translate_on

      next_A = AA + A;
      next_B = BB + B;
      next_C = CC + C;
      next_D = DD + D;

      next_state = TURN_ARND[7:0];
   end // }
   //----------------------------------------------------------------

   // One cycle for making the system to come to reset state
   current_state[TURN_ARND_BIT]: 
   begin // {
      // synopsys translate_off
      ascii_state = "TURN_ARND";
      // synopsys translate_on

      next_state = IDLE[7:0];
   end // }
 
   endcase 
end // }

//--------------------------------
//
// Flops and other combinatorial 
// logic definition
//
//--------------------------------

// Outputs
assign msg_output = {{A[24:31], A[16:23], A[8:15], A[0:7]}
                    ,{B[24:31], B[16:23], B[8:15], B[0:7]}
		    ,{C[24:31], C[16:23], C[8:15], C[0:7]}
		    ,{D[24:31], D[16:23], D[8:15], D[0:7]}};
always @(posedge clk)
   msg_out_valid <= current_state[FINISH_OFF_BIT];

assign ready = current_state[IDLE_BIT];

// Internal scratch pads
always @(posedge clk) 
   if (next_state[ROUND1_BIT] && current_state[IDLE_BIT]) begin // {
      AA <= A;
      BB <= B;
      CC <= C;
      DD <= D;
   end // }

// Initialize A, B, C and D and then compute them
always @(posedge clk) 
   if (rst ) begin // { 
      A <= SALT_A;
      B <= SALT_B;
      C <= SALT_C;
      D <= SALT_D;
   end // }
   else begin // {
      A <= next_A;
      B <= next_B;
      C <= next_C;
      D <= next_D;
   end // }

// Determine one of the 16 phases within each round
always @(posedge clk)
   if (rst) 
      phase <= 4'b0;
   else if (next_state[ROUND1_BIT] && current_state[IDLE_BIT])
      phase <= 4'b0;
   else 
      phase <= phase + 4'b1;

// Assign current_state based on rst and the next_state
always @(posedge clk)
   if (rst) 
      current_state <= IDLE[7:0];
   else 
      current_state <= next_state;
endmodule

fpga_hardware/cores/md5/md5_top.v
module md5_top(
		 wb_adr_i, wb_cyc_i, wb_dat_i, wb_sel_i,
		 wb_stb_i, wb_we_i,
		 wb_ack_o, wb_err_o, wb_dat_o,
		 wb_clk_i, wb_rst_i, int_o
);

   parameter dw = 32;
   parameter aw = 32;

   input [aw-1:0]	wb_adr_i;
   input 		wb_cyc_i;
   input [dw-1:0] 	wb_dat_i;
   input [3:0] 		wb_sel_i;
   input 		wb_stb_i;
   input 		wb_we_i;
   
   output 		wb_ack_o;
   output 		wb_err_o;
   output reg [dw-1:0] 	wb_dat_o;
   output		int_o;

   input 		wb_clk_i;
   input 		wb_rst_i;

   assign wb_ack_o = 1'b1;
   assign wb_err_o = 1'b0;
   assign int_o = 1'b0;

   // Internal registers
   reg startHash;
   reg [31:0] data [0:15];
   reg message_reset;

  /* verilator lint_off LITENDIAN */
  wire [0:511] bigData = {data[0], data[1], data[2], data[3], data[4], data[5], data[6], data[7], data[8], data[9], data[10], data[11], data[12], data[13], data[14], data[15]};
  wire [0:127] hash;
  wire ready;
  wire hashValid;

   // Implement MD5 I/O memory map interface
   // Write side
   always @(posedge wb_clk_i) begin
     if(wb_rst_i) begin
       startHash <= 0;
       message_reset <= 0;
       data[0] <= 0;
       data[1] <= 0;
       data[2] <= 0;
       data[3] <= 0;
       data[4] <= 0;
       data[5] <= 0;
       data[6] <= 0;
       data[7] <= 0;
       data[8] <= 0;
       data[9] <= 0;
       data[10] <= 0;
       data[11] <= 0;
       data[12] <= 0;
       data[13] <= 0;
       data[14] <= 0;
       data[15] <= 0;
     end
     else if(wb_stb_i & wb_we_i) begin
       case(wb_adr_i[6:2])
         0: startHash <= wb_dat_i[0];
         1: data[15] <= wb_dat_i;
         2: data[14] <= wb_dat_i;
         3: data[13] <= wb_dat_i;
         4: data[12] <= wb_dat_i;
         5: data[11] <= wb_dat_i;
         6: data[10] <= wb_dat_i;
         7: data[9] <= wb_dat_i;
         8: data[8] <= wb_dat_i;
         9: data[7] <= wb_dat_i;
         10: data[6] <= wb_dat_i;
         11: data[5] <= wb_dat_i;
         12: data[4] <= wb_dat_i;
         13: data[3] <= wb_dat_i;
         14: data[2] <= wb_dat_i;
         15: data[1] <= wb_dat_i;
         16: data[0] <= wb_dat_i;
         22: message_reset <= wb_dat_i[0];
         default: ;
       endcase
     end
   end

   // Implement MD5 I/O memory map interface
   // Read side
   always @(*) begin
       case(wb_adr_i[6:2])
         0: wb_dat_o = {31'b0, ready};
         1: wb_dat_o = data[15];
         2: wb_dat_o = data[14];
         3: wb_dat_o = data[13];
         4: wb_dat_o = data[12];
         5: wb_dat_o = data[11];
         6: wb_dat_o = data[10];
         7: wb_dat_o = data[9];
         8: wb_dat_o = data[8];
         9: wb_dat_o = data[7];
         10: wb_dat_o = data[6];
         11: wb_dat_o = data[5];
         12: wb_dat_o = data[4];
         13: wb_dat_o = data[3];
         14: wb_dat_o = data[2];
         15: wb_dat_o = data[1];
         16: wb_dat_o = data[0];
         17: wb_dat_o = {31'b0, hashValid};
         21: wb_dat_o = hash[0:31];
         20: wb_dat_o = hash[32:63];
         19: wb_dat_o = hash[64:95];
         18: wb_dat_o = hash[96:127];
         default: wb_dat_o = 32'b0;
       endcase
   end

  pancham pancham(
    .clk(wb_clk_i),
    .rst(wb_rst_i | message_reset),
    .msg_padded(bigData),
    .msg_in_valid(startHash),
    .msg_output(hash),
    .msg_out_valid(hashValid),
    .ready(ready)
  );

endmodule

fpga_hardware/cores/md5/Vmd5_top.vcd
$version Generated by VerilatedVcd $end
$date Fri Jun 16 07:26:16 2017
 $end
$timescale   1ns $end

 $scope module TOP $end
  $var wire  1 T int_o $end
  $var wire  1 Q wb_ack_o $end
  $var wire 32 K wb_adr_i [31:0] $end
  $var wire  1 U wb_clk_i $end
  $var wire  1 L wb_cyc_i $end
  $var wire 32 M wb_dat_i [31:0] $end
  $var wire 32 S wb_dat_o [31:0] $end
  $var wire  1 R wb_err_o $end
  $var wire  1 V wb_rst_i $end
  $var wire  4 N wb_sel_i [3:0] $end
  $var wire  1 O wb_stb_i $end
  $var wire  1 P wb_we_i $end
  $scope module md5_top $end
   $var wire 32 W aw [31:0] $end
   $var wire 512 # bigData [0:511] $end
   $var wire 32 8 data(0) [31:0] $end
   $var wire 32 9 data(1) [31:0] $end
   $var wire 32 B data(10) [31:0] $end
   $var wire 32 C data(11) [31:0] $end
   $var wire 32 D data(12) [31:0] $end
   $var wire 32 E data(13) [31:0] $end
   $var wire 32 F data(14) [31:0] $end
   $var wire 32 G data(15) [31:0] $end
   $var wire 32 : data(2) [31:0] $end
   $var wire 32 ; data(3) [31:0] $end
   $var wire 32 < data(4) [31:0] $end
   $var wire 32 = data(5) [31:0] $end
   $var wire 32 > data(6) [31:0] $end
   $var wire 32 ? data(7) [31:0] $end
   $var wire 32 @ data(8) [31:0] $end
   $var wire 32 A data(9) [31:0] $end
   $var wire 32 W dw [31:0] $end
   $var wire 128 3 hash [0:127] $end
   $var wire  1 J hashValid $end
   $var wire  1 T int_o $end
   $var wire  1 H message_reset $end
   $var wire  1 I ready $end
   $var wire  1 7 startHash $end
   $var wire  1 Q wb_ack_o $end
   $var wire 32 K wb_adr_i [31:0] $end
   $var wire  1 U wb_clk_i $end
   $var wire  1 L wb_cyc_i $end
   $var wire 32 M wb_dat_i [31:0] $end
   $var wire 32 S wb_dat_o [31:0] $end
   $var wire  1 R wb_err_o $end
   $var wire  1 V wb_rst_i $end
   $var wire  4 N wb_sel_i [3:0] $end
   $var wire  1 O wb_stb_i $end
   $var wire  1 P wb_we_i $end
  $upscope $end
 $upscope $end
$enddefinitions $end


#0
b00000000000000000000000000000000000000000000000000000000000000000000000000000000000000000000000000000000000000000000000000000000000000000000000000000000000000000000000000000000000000000000000000000000000000000000000000000000000000000000000000000000000000000000000000000000000000000000000000000000000000000000000000000000000000000000000000000000000000000000000000000000000000000000000000000000000000000000000000000000000000000000000000000000000000000000000000000000000000000000000000000000000000000000000000000000 #
b00000000000000000000000000000000000000000000000000000000000000000000000000000000000000000000000000000000000000000000000000000000 3
07
b00000000000000000000000000000000 8
b00000000000000000000000000000000 9
b00000000000000000000000000000000 :
b00000000000000000000000000000000 ;
b00000000000000000000000000000000 <
b00000000000000000000000000000000 =
b00000000000000000000000000000000 >
b00000000000000000000000000000000 ?
b00000000000000000000000000000000 @
b00000000000000000000000000000000 A
b00000000000000000000000000000000 B
b00000000000000000000000000000000 C
b00000000000000000000000000000000 D
b00000000000000000000000000000000 E
b00000000000000000000000000000000 F
b00000000000000000000000000000000 G
0H
0I
0J
b00000000000000000000000000000000 K
0L
b00000000000000000000000000000000 M
b1111 N
0O
0P
1Q
0R
b00000000000000000000000000000000 S
0T
1U
1V
b00000000000000000000000000100000 W
#2
b00000001001000110100010101100111100010011010101111001101111011111111111011011100101110101001100001110110010101000011001000010000 3
1I
b00000000000000000000000000000001 S
0U
#4
1U
#6
0U
#8
1U
#10
0U
#12
1U
#14
0U
#16
1U
#18
0U
#20
1U
#22
0U
#24
1U
#26
0U
#28
1U
#30
0U
#32
1U
#34
0U
#36
1U
#38
0U
#40
1U
#42
0U
#44
1U
#46
0U
#48
1U
#50
0U
#52
1U
#54
0U
#56
1U
#58
0U
#60
1U
#62
0U
#64
1U
#66
0U
#68
1U
#70
0U
#72
1U
#74
0U
#76
1U
#78
0U
#80
b10010010000000000000000001011000 K
b00000000000000000000000000000001 M
1O
1P
b00000000000000000000000000000000 S
1U
0V
#82
1H
0U
#84
1U
#86
0U
#88
1U
#90
0U
#92
1U
#94
0U
#96
1U
#98
0U
#100
1U
#102
0U
#104
1U
#106
0U
#108
1U
#110
0U
#112
1U
#114
0U
#116
1U
#118
0U
#120
1U
#122
0U
#124
1U
#126
0U
#128
1U
#130
0U
#132
1U
#134
0U
#136
1U
#138
0U
#140
1U
#142
0U
#144
1U
#146
0U
#148
1U
#150
0U
#152
1U
#154
0U
#156
1U
#158
0U
#160
0O
0P
1U
#162
0U
#164
1U
#166
0U
#168
1U
#170
0U
#172
1U
#174
0U
#176
1U
#178
0U
#180
1U
#182
0U
#184
1U
#186
0U
#188
1U
#190
0U
#192
1U
#194
0U
#196
1U
#198
0U
#200
1U
#202
0U
#204
1U
#206
0U
#208
1U
#210
0U
#212
1U
#214
0U
#216
1U
#218
0U
#220
1U
#222
0U
#224
1U
#226
0U
#228
1U
#230
0U
#232
1U
#234
0U
#236
1U
#238
0U
#240
1U
#242
0U
#244
1U
#246
0U
#248
1U
#250
0U
#252
1U
#254
0U
#256
1U
#258
0U
#260
1U
#262
0U
#264
1U
#266
0U
#268
1U
#270
0U
#272
1U
#274
0U
#276
1U
#278
0U
#280
1U
#282
0U
#284
1U
#286
0U
#288
1U
#290
0U
#292
1U
#294
0U
#296
1U
#298
0U
#300
1U
#302
0U
#304
1U
#306
0U
#308
1U
#310
0U
#312
1U
#314
0U
#316
1U
#318
0U
#320
1U
#322
0U
#324
1U
#326
0U
#328
1U
#330
0U
#332
1U
#334
0U
#336
1U
#338
0U
#340
1U
#342
0U
#344
1U
#346
0U
#348
1U
#350
0U
#352
1U
#354
0U
#356
1U
#358
0U
#360
1U
#362
0U
#364
1U
#366
0U
#368
1U
#370
0U
#372
1U
#374
0U
#376
1U
#378
0U
#380
1U
#382
0U
#384
1U
#386
0U
#388
1U
#390
0U
#392
1U
#394
0U
#396
1U
#398
0U
#400
1U
#402
0U
#404
1U
#406
0U
#408
1U
#410
0U
#412
1U
#414
0U
#416
1U
#418
0U
#420
1U
#422
0U
#424
1U
#426
0U
#428
1U
#430
0U
#432
1U
#434
0U
#436
1U
#438
0U
#440
1U
#442
0U
#444
1U
#446
0U
#448
1U
#450
0U
#452
1U
#454
0U
#456
1U
#458
0U
#460
1U
#462
0U
#464
1U
#466
0U
#468
1U
#470
0U
#472
1U
#474
0U
#476
1U
#478
0U
#480
b00000000000000000000000000000000 M
1O
1P
1U
#482
0H
0U
#484
1U
#486
0U
#488
1U
#490
0U
#492
1U
#494
0U
#496
1U
#498
0U
#500
1U
#502
0U
#504
1U
#506
0U
#508
1U
#510
0U
#512
1U
#514
0U
#516
1U
#518
0U
#520
1U
#522
0U
#524
1U
#526
0U
#528
1U
#530
0U
#532
1U
#534
0U
#536
1U
#538
0U
#540
1U
#542
0U
#544
1U
#546
0U
#548
1U
#550
0U
#552
1U
#554
0U
#556
1U
#558
0U
#560
0O
0P
1U
#562
0U
#564
1U
#566
0U
#568
1U
#570
0U
#572
1U
#574
0U
#576
1U
#578
0U
#580
1U
#582
0U
#584
1U
#586
0U
#588
1U
#590
0U
#592
1U
#594
0U
#596
1U
#598
0U
#600
1U
#602
0U
#604
1U
#606
0U
#608
1U
#610
0U
#612
1U
#614
0U
